argapp/LICENSE
argapp/README.md
argapp/__init__.py
argapp/__init__.pyi
argapp-0.7.2.dist-info/METADATA
argapp-0.7.2.dist-info/WHEEL
argapp-0.7.2.dist-info/RECORD
