Metadata-Version: 2.1
Name: argapp
Version: 0.7.2
Summary: A Python package for CLI application development
Project-URL: Repository, https://github.com/deohayer/argapp.git
Author-email: Volodymyr Zakalyk <volodymyr.zakalyk@gmail.com>
Maintainer-email: Volodymyr Zakalyk <volodymyr.zakalyk@gmail.com>
License: MIT License
Keywords: cli
Classifier: Development Status :: 4 - Beta
Classifier: Intended Audience :: Developers
Classifier: License :: OSI Approved :: MIT License
Classifier: Operating System :: POSIX :: Linux
Classifier: Programming Language :: Python :: 3
Classifier: Programming Language :: Python :: 3.6
Classifier: Programming Language :: Python :: 3.7
Classifier: Programming Language :: Python :: 3.8
Classifier: Programming Language :: Python :: 3.9
Classifier: Programming Language :: Python :: 3.10
Classifier: Programming Language :: Python :: 3.11
Classifier: Topic :: Software Development
Requires-Python: >=3.6
